conifer_analysis/__init__.py
conifer_analysis/_version.py
conifer_analysis/extract.py
conifer_analysis/helpers.py
conifer_analysis/pipeline.py
conifer_analysis/transform.py
conifer_analysis-0.1.0.dist-info/LICENSE
conifer_analysis-0.1.0.dist-info/METADATA
conifer_analysis-0.1.0.dist-info/WHEEL
conifer_analysis-0.1.0.dist-info/top_level.txt
conifer_analysis-0.1.0.dist-info/zip-safe
conifer_analysis-0.1.0.dist-info/RECORD
