Metadata-Version: 2.1
Name: conifer-analysis
Version: 0.1.0
Summary: Post-process conifer output for downstream statistical analysis.
Home-page: https://github.com/Midnighter/conifer-analysis
Download-URL: https://pypi.org/project/conifer-analysis/
Author: Moritz E. Beber
Author-email: midnighter@posteo.net
License: Apache-2.0
Project-URL: Source Code, https://github.com/Midnighter/conifer-analysis
Project-URL: Documentation, https://conifer-analysis.readthedocs.io
Project-URL: Bug Tracker, https://github.com/Midnighter/conifer-analysis/issues
Platform: UNKNOWN
Classifier: Development Status :: 2 - Pre-Alpha
Classifier: Intended Audience :: Science/Research
Classifier: License :: OSI Approved :: Apache Software License
Classifier: Natural Language :: English
Classifier: Operating System :: OS Independent
Classifier: Programming Language :: Python :: 3 :: Only
Classifier: Programming Language :: Python :: 3.8
Classifier: Programming Language :: Python :: 3.9
Classifier: Programming Language :: Python :: 3.10
Classifier: Topic :: Scientific/Engineering :: Bio-Informatics
Requires-Python: >=3.8
License-File: LICENSE
Requires-Dist: dask
Requires-Dist: depinfo
Requires-Dist: numpy
Requires-Dist: pandas
Provides-Extra: dashboard
Requires-Dist: distributed ; extra == 'dashboard'
Requires-Dist: bokeh ; extra == 'dashboard'
Provides-Extra: development
Requires-Dist: black ; extra == 'development'
Requires-Dist: isort ; extra == 'development'
Requires-Dist: tox ; extra == 'development'
